CHANGES.txt
COPYRIGHT.txt
LICENSE.txt
README.txt
bootstrap.py
buildout.cfg
setup.py
src/zope/__init__.py
src/zope.app.securitypolicy.egg-info/PKG-INFO
src/zope.app.securitypolicy.egg-info/SOURCES.txt
src/zope.app.securitypolicy.egg-info/dependency_links.txt
src/zope.app.securitypolicy.egg-info/namespace_packages.txt
src/zope.app.securitypolicy.egg-info/not-zip-safe
src/zope.app.securitypolicy.egg-info/requires.txt
src/zope.app.securitypolicy.egg-info/top_level.txt
src/zope/app/__init__.py
src/zope/app/securitypolicy/__init__.py
src/zope/app/securitypolicy/configure.zcml
src/zope/app/securitypolicy/ftesting.zcml
src/zope/app/securitypolicy/testing.py
src/zope/app/securitypolicy/browser/__init__.py
src/zope/app/securitypolicy/browser/configure.zcml
src/zope/app/securitypolicy/browser/granting.py
src/zope/app/securitypolicy/browser/granting_ftest.txt
src/zope/app/securitypolicy/browser/rolepermissionview.py
src/zope/app/securitypolicy/browser/tests/__init__.py
src/zope/app/securitypolicy/browser/tests/functional.py
src/zope/app/securitypolicy/browser/tests/functional.zcml
src/zope/app/securitypolicy/browser/tests/test_functional.py